ygoutil-0.2.2.dist-info/METADATA
ygoutil-0.2.2.dist-info/WHEEL
ygoutil-0.2.2.dist-info/licenses/LICENSE
ygoutil/__init__.py
ygoutil/__version__.py
ygoutil/card/__init__.py
ygoutil/card/card.py
ygoutil/card/constant.py
ygoutil/card/ids.py
ygoutil/card/misc.py
ygoutil/card/unit.py
ygoutil/dataloader.py
ygoutil/legacy/__init__.py
ygoutil/legacy/card.py
ygoutil/source/__init__.py
ygoutil/source/baige/__init__.py
ygoutil/source/baige/api.py
ygoutil/source/baige/misc.py
ygoutil/source/baige/page.py
ygoutil/source/base.py
ygoutil/source/cdb/__init__.py
ygoutil/source/cdb/misc.py
ygoutil/source/misc.py
ygoutil/source/ourocg.py
ygoutil/sqlbuilder.py
ygoutil/ygoRoom.py
ygoutil-0.2.2.dist-info/RECORD
